fastapi_core/__init__.py
fastapi_core/bucket_driver/__init__.py
fastapi_core/bucket_driver/bucket_driver_abc.py
fastapi_core/bucket_driver/s3_bucket_driver.py
fastapi_core/cache_driver/__init__.py
fastapi_core/cache_driver/cache_driver_abc.py
fastapi_core/cache_driver/in_memory_driver.py
fastapi_core/cache_driver/redis_cache_driver.py
fastapi_core/create_app.py
fastapi_core/database/__init__.py
fastapi_core/database/database.py
fastapi_core/middleware/__init__.py
fastapi_core/middleware/app_middleware.py
fastapi_core/middleware/plugins.py
fastapi_core/model/__init__.py
fastapi_core/model/model_base.py
fastapi_core/model/model_helpers.py
fastapi_core/model/model_mixin.py
fastapi_core/orchestrators/__init__.py
fastapi_core/orchestrators/dependencies_orchestrator.py
fastapi_core/repository/__init__.py
fastapi_core/repository/repository.py
fastapi_core/repository/repository_abc.py
fastapi_core/routes/__init__.py
fastapi_core/routes/health/__init__.py
fastapi_core/routes/health/health_router.py
fastapi_core/routes/health/health_schemas.py
fastapi_core/routes/migrations/__init__.py
fastapi_core/routes/migrations/run_migrations_router.py
fastapi_core/routes/migrations/run_migrations_schemas.py
fastapi_core/service/__init__.py
fastapi_core/service/service.py
fastapi_core/settings.py
fastapi_core/talker/__init__.py
fastapi_core/talker/talker.py
fastapi_core/talker/talker_abc.py
fastapi_core/utils/__init__.py
fastapi_core/utils/app_dependencies_abc.py
fastapi_core/utils/csv_exporter.py
fastapi_core/utils/exceptions.py
fastapi_core/utils/render_description.py
fastapi_core/utils/singleton_meta.py
fastapi_core-1.0.2.dist-info/LICENSE
fastapi_core-1.0.2.dist-info/METADATA
fastapi_core-1.0.2.dist-info/WHEEL
fastapi_core-1.0.2.dist-info/RECORD
